dan_socket/__version__.py
dan_socket/base.py
dan_socket/client.py
dan_socket/event.py
dan_socket/server.py
dan_socket-0.1.0.dist-info/LICENSE.txt
dan_socket-0.1.0.dist-info/METADATA
dan_socket-0.1.0.dist-info/WHEEL
dan_socket-0.1.0.dist-info/top_level.txt
dan_socket-0.1.0.dist-info/RECORD
